{"episode":{"episode":389,"airDate":"2021-04-20","summary":"Discussing the Justice Thomas concurrence in Knight v. Trump","crowdcastURL":"https://www.crowdcast.io/e/in-lieu-of-fun-episode-14","youTubeURL":"https://www.youtube.com/watch?v=U6MNvbmepC8","guestNames":["Jameel Jaffer"],"transcriptPath":"/transcripts/transcript-0389.json","detail":"Jameel Jaffer returns to dish on Justice Thomas's concurrence in Knight Institute v. Trump (with Kate), and chat about the new demands for access to FISA Courts records (with Ben)."}}