{"episode":{"episode":418,"airDate":"2021-05-19","crowdcastURL":"https://www.crowdcast.io/e/in-lieu-of-fun-episode-43","youTubeURL":"https://www.youtube.com/watch?v=cbX4pp4pUwI","guestNames":["Jordan Ellenberg"],"transcriptPath":"/transcripts/transcript-0418.json","links":[{"title":"Book","url":"https://www.penguinrandomhouse.com/books/612131/shape-by-jordan-ellenberg/"}],"detail":"We are joined by University of Wisconsin mathematician Jordan Ellenberg, who has a new book out: \"[Shape: The Hidden Geometry of Information, Biology, Strategy, Democracy, and Everything Else][book]\".\n\n[book]: https://www.penguinrandomhouse.com/books/612131/shape-by-jordan-ellenberg/"}}