{"episode":{"episode":477,"airDate":"2021-07-23","summary":"Cheese night! 🧀","crowdcastURL":"https://www.crowdcast.io/e/in-lieu-of-fun-episode-102","youTubeURL":"https://www.youtube.com/watch?v=RIXajCuML8g","acastURL":"https://shows.acast.com/in-lieu-of-fun/episodes/cheese-night-with-a-live-chicken-and-a-muppet","audioFileURL":"https://sphinx.acast.com/p/open/s/6071b87945e5c6581e2e5575/e/60fc531c709b370013728658/media.mp3","transcriptPath":"/transcripts/transcript-0477.json","tags":["cheese-night"]}}