{"episode":{"episode":489,"airDate":"2021-08-10","summary":"Discussing the Facebook lawsuits, election advertisements, and Kate","crowdcastURL":"https://www.crowdcast.io/e/in-lieu-of-fun-episode-114","youTubeURL":"https://www.youtube.com/watch?v=KsVNc6B3L4g","acastURL":"https://shows.acast.com/in-lieu-of-fun/episodes/seth-magaziner-treasures-rhode-island","audioFileURL":"https://sphinx.acast.com/p/open/s/6071b87945e5c6581e2e5575/e/61141989ec696c0012766fce/media.mp3","guestNames":["Seth Magaziner"],"transcriptPath":"/transcripts/transcript-0489.json"}}